[
  {
    "id": 6,
    "songTitle": "November",
    "songArtist": "Royalty Free Music from Bensound",
    "albumCover": "https://i.esdrop.com/d/f/WFi7Wlweew/VEgBNprL1a.jpg",
    "content": "https://www.bensound.com/bensound-music/bensound-november.mp3"
  },
  {
    "id": 7,
    "songTitle": "Photo Album",
    "songArtist": "Royalty Free Music from Bensound",
    "albumCover": "https://i.esdrop.com/d/f/WFi7Wlweew/s31ixS7d2q.jpg",
    "content": "https://www.bensound.com/bensound-music/bensound-photoalbum.mp3"
  },
  {
    "id": 8,
    "songTitle": "Adventure",
    "songArtist": "Royalty Free Music from Bensound",
    "albumCover": "https://i.esdrop.com/d/f/WFi7Wlweew/3JckjOZrZe.jpg",
    "content": "https://www.bensound.com/bensound-music/bensound-adventure.mp3"
  },
  {
    "id": 9,
    "songTitle": "Once Again",
    "songArtist": "Royalty Free Music from Bensound",
    "albumCover": "https://i.esdrop.com/d/f/WFi7Wlweew/SRNyOvPM11.png",
    "content": "https://www.bensound.com/bensound-music/bensound-onceagain.mp3"
  },
  {
    "id": 10,
    "songTitle": "E. R. F",
    "songArtist": "Royalty Free Music from Bensound",
    "albumCover": "https://i.esdrop.com/d/f/WFi7Wlweew/5c1soPR5by.jpg",
    "content": "https://www.bensound.com/bensound-music/bensound-erf.mp3"
  }
]
